common/__init__.py
common/decos.py
common/descryptors.py
common/errors.py
common/metaclasses.py
common/utils.py
common/variables.py
logs/__init__.py
logs/config_server_log.py
server/__init__.py
server/add_user.py
server/config_window.py
server/core.py
server/database.py
server/main_window.py
server/remove_user.py
server/stat_window.py
unit_tests/__init__.py
chat_server_GB_course_april-0.1.dist-info/METADATA
chat_server_GB_course_april-0.1.dist-info/WHEEL
chat_server_GB_course_april-0.1.dist-info/top_level.txt
chat_server_GB_course_april-0.1.dist-info/RECORD
