Metadata-Version: 2.1
Name: chat-server-GB-course-april
Version: 0.1
Summary: Server packet
Author: Andrei Kasyyanyk
Author-email: fantom-gtn@list.ru
